ferrobus-0.1.8.dist-info/METADATA
ferrobus-0.1.8.dist-info/WHEEL
ferrobus-0.1.8.dist-info/licenses/LICENSE-APACHE
ferrobus-0.1.8.dist-info/licenses/LICENSE-MIT
ferrobus/__init__.py
ferrobus/__init__.pyi
ferrobus/ferrobus.cpython-313-x86_64-linux-gnu.so
ferrobus/py.typed
ferrobus-0.1.8.dist-info/RECORD
