Metadata-Version: 2.4
Name: ferrobus
Version: 0.1.8
Classifier: Programming Language :: Rust
Classifier: Programming Language :: Python :: Implementation :: CPython
Classifier: Programming Language :: Python :: Implementation :: PyPy
Classifier: Development Status :: 2 - Pre-Alpha
Classifier: Intended Audience :: Science/Research
Classifier: License :: OSI Approved :: MIT License
Classifier: License :: OSI Approved :: Apache Software License
Classifier: Operating System :: Microsoft :: Windows
Classifier: Operating System :: POSIX :: Linux
Classifier: Operating System :: MacOS
Classifier: Topic :: Scientific/Engineering :: GIS
Classifier: Topic :: Scientific/Engineering :: Information Analysis
Classifier: Topic :: Scientific/Engineering :: Visualization
Requires-Dist: myst-nb ; extra == 'docs'
Requires-Dist: sphinx-book-theme ; extra == 'docs'
Provides-Extra: docs
License-File: LICENSE-APACHE
License-File: LICENSE-MIT
Summary: High-performance multimodal public transit routing library 
License: MIT OR Apache-2.0
Requires-Python: >=3.8
Project-URL: Homepage, https://github.com/chingiztob/ferrobus
Project-URL: Documentation, https://ferrobus.readthedocs.io/
